{
  "context": {
    "introduction": "Explore the art of Korean marinades and grilled meats. Learn how time and ingredients create tender, flavorful dishes.",
    "sections": [
      {
        "title": "Natural Tenderizers",
        "icon": "Target",
        "content": "Korean marinades often include ingredients like Asian pear and soy sauce to tenderize meat."
      },
      {
        "title": "Marination Time",
        "icon": "Sparkles",
        "content": "Proper marination requires patience. The right timing develops flavor while ensuring tenderness."
      },
      {
        "title": "Meat Selection",
        "icon": "BookOpen",
        "content": "Different cuts of meat are used for different dishes, each bringing unique texture and flavor."
      },
      {
        "title": "Grilling Tips",
        "icon": "LightbulbIcon",
        "listItems": [
          "Slice meat thin for quick cooking",
          "Marinate overnight for best flavor",
          "Use a hot grill for caramelization"
        ]
      }
    ]
  }
} 